torch_qu-0.1.4.dist-info/licenses/LICENSE
torchq/__init__.py
torchq/func/__init__.py
torchq/func/fisher.py
torchq/models/__init__.py
torchq/models/qnn.py
torchq/nn/__init__.py
torchq/nn/functional.py
torchq/nn/init.py
torchq/nn/layers.py
torchq/optim/__init__.py
torchq/quantum/__init__.py
torchq/quantum/base.py
torchq/quantum/blocks.py
torchq/quantum/feature_maps/__init__.py
torchq/quantum/feature_maps/base.py
torchq/quantum/feature_maps/pauli.py
torchq/quantum/feature_maps/z_feature_map.py
torchq/quantum/feature_maps/zz_feature_map.py
torchq/quantum/variational_forms/__init__.py
torchq/quantum/variational_forms/base.py
torchq/quantum/variational_forms/efficient_su2.py
torchq/quantum/variational_forms/n_local.py
torchq/quantum/variational_forms/pauli_two_design.py
torchq/quantum/variational_forms/real_amplitudes.py
torch_qu-0.1.4.dist-info/METADATA
torch_qu-0.1.4.dist-info/WHEEL
torch_qu-0.1.4.dist-info/top_level.txt
torch_qu-0.1.4.dist-info/RECORD
