Metadata-Version: 2.4
Name: torch-qu
Version: 0.1.4
Summary: PyTorch-style quantum-ML layers that run on CPUs, GPUs or real QPUs via NVIDIA CUDA-Q
Author-email: Sergio Rodríguez Vidal <serovi@alu.comillas.edu>
License:                                  Apache License
Project-URL: Homepage, https://github.com/SeroviICAI/torch-quantum
Project-URL: Bug Tracker, https://github.com/SeroviICAI/torch-quantum/issues
Keywords: quantum,artificial-intelligence,machine-learning,pytorch,quantum-computing,cuda-quantum
Classifier: Development Status :: 3 - Alpha
Classifier: License :: OSI Approved :: Apache Software License
Classifier: Programming Language :: Python :: 3
Classifier: Programming Language :: Python :: 3 :: Only
Classifier: Programming Language :: Python :: 3.9
Classifier: Topic :: Scientific/Engineering :: Artificial Intelligence
Requires-Python: >=3.8
License-File: LICENSE
Requires-Dist: torch>=1.13
Requires-Dist: numpy>=1.20
Dynamic: license-file
